dbus_next/__init__.py
dbus_next/__version__.py
dbus_next/auth.py
dbus_next/constants.py
dbus_next/errors.py
dbus_next/introspection.py
dbus_next/message.py
dbus_next/message_bus.py
dbus_next/proxy_object.py
dbus_next/service.py
dbus_next/signature.py
dbus_next/validators.py
dbus_next/_private/__init__.py
dbus_next/_private/address.py
dbus_next/_private/constants.py
dbus_next/_private/marshaller.py
dbus_next/_private/unmarshaller.py
dbus_next/_private/util.py
dbus_next/aio/__init__.py
dbus_next/aio/message_bus.py
dbus_next/aio/proxy_object.py
dbus_next/glib/__init__.py
dbus_next/glib/message_bus.py
dbus_next/glib/proxy_object.py
dbus_next-0.2.2.dist-info/LICENSE
dbus_next-0.2.2.dist-info/METADATA
dbus_next-0.2.2.dist-info/WHEEL
dbus_next-0.2.2.dist-info/top_level.txt
dbus_next-0.2.2.dist-info/RECORD
