Metadata-Version: 2.1
Name: dbus_next
Version: 0.2.2
Summary: A zero-dependency DBus library for Python with asyncio support
Home-page: https://github.com/altdesktop/python-dbus-next
Author: Tony Crisci
Author-email: tony@dubstepdish.com
License: MIT
Platform: UNKNOWN
Classifier: Development Status :: 3 - Alpha
Classifier: Environment :: X11 Applications
Classifier: Environment :: X11 Applications :: Gnome
Classifier: Topic :: Desktop Environment :: Gnome
Classifier: Topic :: Software Development :: Embedded Systems
Classifier: Framework :: AsyncIO
Classifier: License :: OSI Approved :: MIT License
Classifier: Programming Language :: Python
Classifier: Programming Language :: Python :: 3
Classifier: Programming Language :: Python :: 3.6
Classifier: Programming Language :: Python :: 3.7
Classifier: Programming Language :: Python :: Implementation :: CPython
Classifier: Programming Language :: Python :: Implementation :: PyPy
Classifier: Typing :: Typed
Requires-Python: >=3.6.0
